[{"id":1,"brand":"White, Cronin and White","model":"50730-8712","serial_number":2747649097,"price":19217,"quantity":310,"availability":true,"made_in_country":"United States","rate":5},
{"id":2,"brand":"Pfeffer, Macejkovic and Leannon","model":"61957-0310","serial_number":2879733746,"price":12286,"quantity":70,"availability":false,"made_in_country":"Portugal","rate":2},
{"id":3,"brand":"Harris-Stroman","model":"76138-103","serial_number":2746468089,"price":7512,"quantity":277,"availability":true,"made_in_country":"United States","rate":5},
{"id":4,"brand":"Baumbach-Hills","model":"55346-0401","serial_number":2541519827,"price":12611,"quantity":91,"availability":true,"made_in_country":"Poland","rate":2},
{"id":5,"brand":"Ryan-O'Kon","model":"40104-002","serial_number":2915496255,"price":17589,"quantity":224,"availability":false,"made_in_country":"Portugal","rate":2},
{"id":6,"brand":"Breitenberg-Gibson","model":"55289-171","serial_number":2933392973,"price":15868,"quantity":170,"availability":false,"made_in_country":"United States","rate":4},
{"id":7,"brand":"Price, Orn and Smitham","model":"49738-695","serial_number":2473005441,"price":11886,"quantity":223,"availability":true,"made_in_country":"Poland","rate":1},
{"id":8,"brand":"Ortiz, Russel and Walter","model":"65862-250","serial_number":2903572650,"price":2716,"quantity":192,"availability":false,"made_in_country":"Portugal","rate":1},
{"id":9,"brand":"Jast, Denesik and Fahey","model":"68788-9399","serial_number":2579454664,"price":1807,"quantity":284,"availability":false,"made_in_country":"United States","rate":4},
{"id":10,"brand":"Roberts, Powlowski and Littel","model":"67296-0677","serial_number":2231981117,"price":9946,"quantity":181,"availability":false,"made_in_country":"Poland","rate":5},
{"id":11,"brand":"Boyle-Jakubowski","model":"46122-211","serial_number":2123645069,"price":10853,"quantity":194,"availability":true,"made_in_country":"Portugal","rate":2},
{"id":12,"brand":"Hills, Nader and Lesch","model":"49738-903","serial_number":2918306304,"price":12541,"quantity":333,"availability":true,"made_in_country":"United States","rate":1},
{"id":13,"brand":"Walter-Keeling","model":"57841-1305","serial_number":2646097040,"price":4943,"quantity":69,"availability":false,"made_in_country":"Germany","rate":3},
{"id":14,"brand":"Herman Inc","model":"51346-185","serial_number":2251940017,"price":1116,"quantity":217,"availability":true,"made_in_country":"Portugal","rate":4},
{"id":15,"brand":"Hyatt, Schmidt and Pollich","model":"50222-503","serial_number":2793459436,"price":11932,"quantity":158,"availability":true,"made_in_country":"United States","rate":2},
{"id":16,"brand":"Nikolaus Group","model":"52125-334","serial_number":2693990211,"price":2548,"quantity":131,"availability":true,"made_in_country":"Poland","rate":5},
{"id":17,"brand":"Lebsack Inc","model":"0615-5619","serial_number":2611733410,"price":542,"quantity":282,"availability":true,"made_in_country":"Portugal","rate":2},
{"id":18,"brand":"Douglas and Sons","model":"65044-1788","serial_number":2836266184,"price":8435,"quantity":160,"availability":false,"made_in_country":"Poland","rate":5},
{"id":19,"brand":"Hauck LLC","model":"49430-007","serial_number":2439252839,"price":11671,"quantity":171,"availability":true,"made_in_country":"Poland","rate":3},
{"id":20,"brand":"Champlin LLC","model":"51285-131","serial_number":2745952161,"price":10306,"quantity":109,"availability":true,"made_in_country":"Poland","rate":4},
{"id":21,"brand":"Luettgen, Osinski and Monahan","model":"54458-887","serial_number":2537597720,"price":10728,"quantity":216,"availability":false,"made_in_country":"United States","rate":2},
{"id":22,"brand":"Sporer Inc","model":"57664-634","serial_number":2461269705,"price":2182,"quantity":162,"availability":true,"made_in_country":"Switzerland","rate":4},
{"id":23,"brand":"Kulas, Jacobson and Hayes","model":"68151-0092","serial_number":2861355364,"price":13896,"quantity":364,"availability":true,"made_in_country":"Poland","rate":5},
{"id":24,"brand":"Sporer Inc","model":"41167-7516","serial_number":2163617313,"price":15304,"quantity":282,"availability":false,"made_in_country":"Poland","rate":2},
{"id":25,"brand":"Hagenes, Hauck and Yost","model":"61919-171","serial_number":2074482511,"price":18976,"quantity":25,"availability":true,"made_in_country":"Germany","rate":3},
{"id":26,"brand":"Williamson, Kuhn and Larkin","model":"76074-122","serial_number":2049688361,"price":3395,"quantity":77,"availability":false,"made_in_country":"Portugal","rate":3},
{"id":27,"brand":"Shields-Carroll","model":"68685-0001","serial_number":2380298857,"price":2699,"quantity":4,"availability":true,"made_in_country":"United States","rate":1},
{"id":28,"brand":"Marquardt, Borer and Simonis","model":"49349-943","serial_number":2387937725,"price":9383,"quantity":8,"availability":false,"made_in_country":"United States","rate":3},
{"id":29,"brand":"Kshlerin, Brown and Herzog","model":"53217-024","serial_number":2711456198,"price":17698,"quantity":203,"availability":true,"made_in_country":"United States","rate":5},
{"id":30,"brand":"Bosco-Jacobs","model":"31722-520","serial_number":2792073316,"price":16521,"quantity":398,"availability":true,"made_in_country":"Portugal","rate":3},
{"id":31,"brand":"Tillman Inc","model":"46122-013","serial_number":2481584784,"price":8665,"quantity":106,"availability":true,"made_in_country":"Portugal","rate":5},
{"id":32,"brand":"Ebert LLC","model":"0603-5486","serial_number":2594390763,"price":16382,"quantity":260,"availability":true,"made_in_country":"Poland","rate":2},
{"id":33,"brand":"Grady and Sons","model":"60505-0823","serial_number":2835738260,"price":807,"quantity":249,"availability":true,"made_in_country":"Portugal","rate":4},
{"id":34,"brand":"Kovacek, Tromp and Koelpin","model":"54569-3439","serial_number":2990570101,"price":3201,"quantity":303,"availability":true,"made_in_country":"Poland","rate":1},
{"id":35,"brand":"Crona Group","model":"44117-0002","serial_number":2278479300,"price":3321,"quantity":262,"availability":true,"made_in_country":"United States","rate":3},
{"id":36,"brand":"Medhurst-Swaniawski","model":"16590-897","serial_number":2976971598,"price":1266,"quantity":22,"availability":false,"made_in_country":"Portugal","rate":5},
{"id":37,"brand":"McLaughlin-Walsh","model":"33992-1070","serial_number":2110284253,"price":831,"quantity":297,"availability":false,"made_in_country":"Poland","rate":4},
{"id":38,"brand":"Keebler Group","model":"68788-9692","serial_number":2825567886,"price":11015,"quantity":81,"availability":false,"made_in_country":"United States","rate":1},
{"id":39,"brand":"Kihn-Jenkins","model":"0003-4222","serial_number":2620021608,"price":262,"quantity":62,"availability":true,"made_in_country":"Portugal","rate":3},
{"id":40,"brand":"Lang Group","model":"67777-222","serial_number":2085229955,"price":12486,"quantity":314,"availability":false,"made_in_country":"Poland","rate":2},
{"id":41,"brand":"Funk and Sons","model":"21695-393","serial_number":2828319463,"price":15861,"quantity":31,"availability":true,"made_in_country":"Portugal","rate":4},
{"id":42,"brand":"Keebler-Keeling","model":"55648-782","serial_number":2889585742,"price":9436,"quantity":52,"availability":false,"made_in_country":"United States","rate":2},
{"id":43,"brand":"Block Group","model":"54575-431","serial_number":2280655152,"price":16502,"quantity":247,"availability":true,"made_in_country":"Portugal","rate":1},
{"id":44,"brand":"Macejkovic and Sons","model":"0699-5750","serial_number":2533208110,"price":14939,"quantity":53,"availability":false,"made_in_country":"Poland","rate":3},
{"id":45,"brand":"Stehr, Stiedemann and Friesen","model":"62584-452","serial_number":2423561785,"price":1159,"quantity":223,"availability":false,"made_in_country":"Belgium","rate":5},
{"id":46,"brand":"Hodkiewicz and Sons","model":"63742-001","serial_number":2960446912,"price":17692,"quantity":253,"availability":true,"made_in_country":"Switzerland","rate":5},
{"id":47,"brand":"Blanda-Green","model":"62756-581","serial_number":2298912519,"price":38,"quantity":183,"availability":false,"made_in_country":"Portugal","rate":4},
{"id":48,"brand":"Paucek-Rosenbaum","model":"51346-079","serial_number":2924659397,"price":10386,"quantity":31,"availability":false,"made_in_country":"Germany","rate":2},
{"id":49,"brand":"Hodkiewicz and Sons","model":"16590-481","serial_number":2240850888,"price":1962,"quantity":377,"availability":false,"made_in_country":"Poland","rate":1},
{"id":50,"brand":"Howe, Walker and Grady","model":"63629-1533","serial_number":2820319590,"price":9440,"quantity":252,"availability":true,"made_in_country":"United States","rate":2},
{"id":51,"brand":"Harris Inc","model":"61715-083","serial_number":2108517641,"price":14250,"quantity":109,"availability":false,"made_in_country":"Portugal","rate":2},
{"id":52,"brand":"Buckridge-Harvey","model":"48951-8085","serial_number":2710408348,"price":7982,"quantity":28,"availability":true,"made_in_country":"Switzerland","rate":2},
{"id":53,"brand":"Waelchi Group","model":"37000-088","serial_number":2958062778,"price":12179,"quantity":263,"availability":true,"made_in_country":"Portugal","rate":5},
{"id":54,"brand":"Hand, Gerhold and Olson","model":"57664-397","serial_number":2968617868,"price":8412,"quantity":249,"availability":false,"made_in_country":"Poland","rate":4},
{"id":55,"brand":"Torp, Parker and Herman","model":"0088-2223","serial_number":2421395302,"price":14041,"quantity":174,"availability":false,"made_in_country":"Germany","rate":4},
{"id":56,"brand":"Walsh Group","model":"49349-932","serial_number":2395452488,"price":6386,"quantity":128,"availability":true,"made_in_country":"United States","rate":4},
{"id":57,"brand":"Walter, Schmidt and Schowalter","model":"52125-444","serial_number":2636651966,"price":6351,"quantity":70,"availability":false,"made_in_country":"Poland","rate":5},
{"id":58,"brand":"Grant-Casper","model":"17238-193","serial_number":2489912818,"price":18624,"quantity":42,"availability":true,"made_in_country":"United Kingdom","rate":5},
{"id":59,"brand":"Thompson-Kunze","model":"41163-810","serial_number":2064358245,"price":1057,"quantity":173,"availability":true,"made_in_country":"Poland","rate":5},
{"id":60,"brand":"Goyette Inc","model":"64483-007","serial_number":2610640616,"price":9784,"quantity":85,"availability":true,"made_in_country":"Switzerland","rate":1},
{"id":61,"brand":"Willms, Swaniawski and Funk","model":"0054-8858","serial_number":2414668808,"price":16877,"quantity":4,"availability":true,"made_in_country":"United States","rate":2},
{"id":62,"brand":"Rohan and Sons","model":"42549-620","serial_number":2934228458,"price":11488,"quantity":6,"availability":false,"made_in_country":"United Kingdom","rate":3},
{"id":63,"brand":"Heller Group","model":"68391-267","serial_number":2791311417,"price":1641,"quantity":217,"availability":false,"made_in_country":"Poland","rate":4},
{"id":64,"brand":"Dach, Schuppe and Grimes","model":"43406-0009","serial_number":2350691829,"price":2527,"quantity":346,"availability":true,"made_in_country":"Poland","rate":3},
{"id":65,"brand":"Nicolas-Jacobson","model":"0143-9965","serial_number":2630128385,"price":15549,"quantity":251,"availability":false,"made_in_country":"Poland","rate":2},
{"id":66,"brand":"Quigley, Metz and Franecki","model":"34690-9001","serial_number":2982177118,"price":18050,"quantity":65,"availability":false,"made_in_country":"Portugal","rate":1},
{"id":67,"brand":"Torphy and Sons","model":"63868-812","serial_number":2259954193,"price":214,"quantity":303,"availability":true,"made_in_country":"Portugal","rate":2},
{"id":68,"brand":"Kreiger-Hoeger","model":"60905-0029","serial_number":2941658088,"price":9987,"quantity":38,"availability":false,"made_in_country":"Switzerland","rate":2},
{"id":69,"brand":"Schimmel, Kemmer and Predovic","model":"57520-0044","serial_number":2545525659,"price":17051,"quantity":309,"availability":false,"made_in_country":"Switzerland","rate":5},
{"id":70,"brand":"Mayert, Barrows and Kling","model":"48951-4059","serial_number":2585469326,"price":16173,"quantity":78,"availability":false,"made_in_country":"Belgium","rate":4},
{"id":71,"brand":"Schuster Group","model":"41268-105","serial_number":2314032598,"price":1797,"quantity":246,"availability":true,"made_in_country":"Portugal","rate":5},
{"id":72,"brand":"Hermiston Inc","model":"43419-747","serial_number":2586858522,"price":881,"quantity":310,"availability":false,"made_in_country":"United States","rate":2},
{"id":73,"brand":"Predovic and Sons","model":"68472-135","serial_number":2640525901,"price":2607,"quantity":99,"availability":true,"made_in_country":"Switzerland","rate":1},
{"id":74,"brand":"Rath, Kuhlman and Durgan","model":"54092-520","serial_number":2392217800,"price":13728,"quantity":173,"availability":true,"made_in_country":"Poland","rate":2},
{"id":75,"brand":"Champlin-Murphy","model":"58118-1391","serial_number":2052357747,"price":1335,"quantity":144,"availability":false,"made_in_country":"United States","rate":4},
{"id":76,"brand":"Cassin Group","model":"55154-3332","serial_number":2255432982,"price":18605,"quantity":139,"availability":false,"made_in_country":"Poland","rate":1},
{"id":77,"brand":"Nikolaus-Spencer","model":"62750-036","serial_number":2712743646,"price":8426,"quantity":184,"availability":true,"made_in_country":"Portugal","rate":1},
{"id":78,"brand":"Nader Group","model":"0113-0517","serial_number":2469888533,"price":5086,"quantity":297,"availability":false,"made_in_country":"Belgium","rate":1},
{"id":79,"brand":"Schamberger Inc","model":"42507-359","serial_number":2183913327,"price":11669,"quantity":159,"availability":false,"made_in_country":"Germany","rate":5},
{"id":80,"brand":"Terry, Hayes and Paucek","model":"65862-299","serial_number":2064612274,"price":6711,"quantity":202,"availability":false,"made_in_country":"Poland","rate":4},
{"id":81,"brand":"Anderson and Sons","model":"41268-588","serial_number":2769035509,"price":8677,"quantity":281,"availability":true,"made_in_country":"United States","rate":1},
{"id":82,"brand":"Swift Group","model":"0268-1319","serial_number":2294063380,"price":19682,"quantity":357,"availability":true,"made_in_country":"Germany","rate":2},
{"id":83,"brand":"Schmeler Inc","model":"0003-0894","serial_number":2129933381,"price":15248,"quantity":255,"availability":true,"made_in_country":"Portugal","rate":1},
{"id":84,"brand":"Smith Group","model":"68428-063","serial_number":2104422220,"price":3993,"quantity":255,"availability":false,"made_in_country":"United States","rate":2},
{"id":85,"brand":"Bruen Group","model":"36987-1568","serial_number":2364166010,"price":17638,"quantity":335,"availability":false,"made_in_country":"Germany","rate":4},
{"id":86,"brand":"Walker Inc","model":"58411-202","serial_number":2158634833,"price":19648,"quantity":29,"availability":true,"made_in_country":"Belgium","rate":4},
{"id":87,"brand":"Blanda, Stanton and Boyer","model":"49348-476","serial_number":2901875649,"price":12480,"quantity":85,"availability":false,"made_in_country":"Portugal","rate":2},
{"id":88,"brand":"Johnson-Denesik","model":"52343-052","serial_number":2720517028,"price":12473,"quantity":334,"availability":false,"made_in_country":"United Kingdom","rate":1},
{"id":89,"brand":"Stanton and Sons","model":"68016-081","serial_number":2175919502,"price":5031,"quantity":150,"availability":false,"made_in_country":"Poland","rate":4},
{"id":90,"brand":"Leuschke LLC","model":"41520-477","serial_number":2561214955,"price":3430,"quantity":310,"availability":true,"made_in_country":"Germany","rate":3},
{"id":91,"brand":"Bechtelar-Wehner","model":"0113-0271","serial_number":2314986699,"price":1068,"quantity":322,"availability":true,"made_in_country":"United Kingdom","rate":3},
{"id":92,"brand":"Langosh-Dicki","model":"64893-902","serial_number":2443073717,"price":18614,"quantity":222,"availability":true,"made_in_country":"Belgium","rate":5},
{"id":93,"brand":"Reichert Group","model":"41250-516","serial_number":2458076794,"price":10619,"quantity":207,"availability":false,"made_in_country":"Portugal","rate":5},
{"id":94,"brand":"Hills, Schaefer and Marvin","model":"50865-688","serial_number":2256906171,"price":2324,"quantity":359,"availability":false,"made_in_country":"United States","rate":5},
{"id":95,"brand":"Douglas, Waters and Batz","model":"57337-030","serial_number":2254939023,"price":9177,"quantity":129,"availability":false,"made_in_country":"Poland","rate":5},
{"id":96,"brand":"Dietrich LLC","model":"43353-908","serial_number":2818732901,"price":1608,"quantity":374,"availability":true,"made_in_country":"Belgium","rate":5},
{"id":97,"brand":"Raynor, Skiles and Sawayn","model":"63629-1765","serial_number":2433230194,"price":6214,"quantity":202,"availability":true,"made_in_country":"Portugal","rate":3},
{"id":98,"brand":"Hartmann, Schuppe and Stanton","model":"72036-223","serial_number":2041618988,"price":6447,"quantity":291,"availability":true,"made_in_country":"United States","rate":5},
{"id":99,"brand":"Buckridge LLC","model":"43598-322","serial_number":2715747957,"price":4402,"quantity":395,"availability":false,"made_in_country":"Belgium","rate":4},
{"id":100,"brand":"Bogisich-Zieme","model":"0143-9966","serial_number":2324222094,"price":7032,"quantity":33,"availability":true,"made_in_country":"United States","rate":3}]
